tnote_plus/__init__.py
tnote_plus/tnote.py
tnote_plus-0.1.0.dist-info/entry_points.txt
tnote_plus-0.1.0.dist-info/LICENSE
tnote_plus-0.1.0.dist-info/WHEEL
tnote_plus-0.1.0.dist-info/METADATA
tnote_plus-0.1.0.dist-info/RECORD
