Metadata-Version: 2.1
Name: tnote-plus
Version: 0.1.0
Summary: simple CLI notetaking
Home-page: https://github.com/acherrera/tnote_plus
License: MIT
Keywords: python3,notetaking,local
Author: Anthony Herrera
Author-email: anthonyherrera24@gmail.com
Requires-Python: >=3.8,<4.0
Classifier: License :: OSI Approved :: MIT License
Classifier: Programming Language :: Python :: 3
Classifier: Programming Language :: Python :: 3.10
Classifier: Programming Language :: Python :: 3.8
Classifier: Programming Language :: Python :: 3.9
Requires-Dist: getkey (>=0.6.5,<0.7.0)
Requires-Dist: peewee (>=3.14.10,<4.0.0)
Requires-Dist: rich (>=12.4.4,<13.0.0)
Project-URL: Repository, https://github.com/acherrera/tnote_plus
